[
    {
        "method": "POST",
        "headers": {
            "Content-Type": "application/json"
        },
        "body": {
            "title": "Monety i banknoty z PRL-u s\u0105 teraz w cenie. W 2025 roku niekt\u00f3re stare pieni\u0105dze warte s\u0105 krocie [25.04.2025 r.]",
            "link": "https://www.msn.com/pl-pl/wiadomosci/other/monety-i-banknoty-z-prl-u-s%C4%85-teraz-w-cenie-w-2025-roku-niekt%C3%B3re-stare-pieni%C4%85dze-warte-s%C4%85-krocie-25042025-r/ar-AA1BZVvo?ocid=BingNewsVerp",
            "description": "Pieni\u0105dze z czas\u00f3w PRL to w 2025 roku prawdziwe skarby dla kolekcjoner\u00f3w i mi\u0142o\u015bnik\u00f3w numizmatyki. Ceny peerelowskich monet i banknot\u00f3w stale rosn\u0105. Co sprawia, \u017ce pieni\u0105dze z PRL s\u0105 tak poszukiwane w ...",
            "image_url": "https://www.bing.pl/th?id=ODF.qEcc-ZyVkvSOSXNTGhpADA&pid=news&w=16&h=16&c=14&rs=2&qlt=90",
            "category": "starocie",
            "date": "Gazeta Pomorska on MSN8 godz.",
            "source": "Gazeta Pomorska on MSN",
            "article_content": ""
        }
    },
    {
        "method": "POST",
        "headers": {
            "Content-Type": "application/json"
        },
        "body": {
            "title": "Krocie za poszukiwane wazony PRL. Tyle w 2025 roku p\u0142ac\u0105 kolekcjonerzy za stare kryszta\u0142owe, porcelanowe i szklane wazony [24.04.25]",
            "link": "https://www.msn.com/pl-pl/historia-i-kultura-spo%C5%82ecze%C5%84stwa/pop-kultura/krocie-za-poszukiwane-wazony-prl-tyle-w-2025-roku-p%C5%82ac%C4%85-kolekcjonerzy-za-stare-kryszta%C5%82owe-porcelanowe-i-szklane-wazony-9-04-25-r/ar-AA1CBMeE?ocid=BingNewsVerp",
            "description": "pochodzenia - wazony z renomowanych hut, takich jak \"Z\u0105bkowice\" czy \"Irena\", s\u0105 bardziej warto\u015bciowe.",
            "image_url": "https://www.bing.pl/th?id=OVF.%2b1wZpISEwXr10vTkliI6Bg&pid=News&w=234&h=132&c=14&rs=2&qlt=30",
            "category": "starocie",
            "date": "Express Bydgoski on MSN8 godz.",
            "source": "Express Bydgoski on MSN",
            "article_content": ""
        }
    },
    {
        "method": "POST",
        "headers": {
            "Content-Type": "application/json"
        },
        "body": {
            "title": "Paulina Musialska",
            "link": "https://dziennikzachodni.pl/autorzy/paulina-musialska/au/723/151",
            "description": "Lista artyku\u0142\u00f3w autora Paulina Musialska w serwisie Dziennik Zachodni. Dane teleadresowe autora oraz linki do jego profili w portalach spo\u0142eczno\u015bciowych.",
            "image_url": "https://www.bing.pl/th?id=ODF.73GKiv_kwPXUhIas-a0ZXQ&pid=news&w=16&h=16&c=14&rs=2&qlt=90",
            "category": "starocie",
            "date": "Dziennik Zachodni22 godz.",
            "source": "Dziennik Zachodni",
            "article_content": "Content not available"
        }
    },
    {
        "method": "POST",
        "headers": {
            "Content-Type": "application/json"
        },
        "body": {
            "title": "Przegl\u0105d prasy 24.04.2025. Zestawili\u015bmy dla Ciebie najwa\u017cniejsze wydarzenia z wczoraj. Zobacz nasz\u0105 pras\u00f3wk\u0119",
            "link": "https://echodnia.eu/przeglad-prasy-24-04-2025-zestawilismy-dla-ciebie-najwazniejsze-wydarzenia-z-wczoraj-zobacz-nasza-prasowke/ar/c1p1-19960913",
            "description": "\u015alub i wesele to jedne z najwa\u017cniejszych wydarze\u0144 w \u017cyciu ka\u017cdej pary, a wyb\u00f3r odpowiedniego miejsca na przyj\u0119cie mo\u017ce by\u0107 ...",
            "image_url": "https://www.bing.pl/th?id=OVFT.jJazG4OEMr4XEbU1kOm0vS&pid=News&w=234&h=132&c=14&rs=2&qlt=30",
            "category": "starocie",
            "date": "Echo Dnia21 godz.",
            "source": "Echo Dnia",
            "article_content": "Content not available"
        }
    },
    {
        "method": "POST",
        "headers": {
            "Content-Type": "application/json"
        },
        "body": {
            "title": "Monety i banknoty z PRL-u s\u0105 teraz w cenie. W 2025 roku niekt\u00f3re stare pieni\u0105dze warte s\u0105 krocie [25.04.2025 r.]",
            "link": "https://www.msn.com/pl-pl/wiadomosci/other/monety-i-banknoty-z-prl-u-s%C4%85-teraz-w-cenie-w-2025-roku-niekt%C3%B3re-stare-pieni%C4%85dze-warte-s%C4%85-krocie-25042025-r/ar-AA1BZVvo?ocid=BingNewsVerp",
            "description": "Pieni\u0105dze z czas\u00f3w PRL to w 2025 roku prawdziwe skarby dla kolekcjoner\u00f3w i mi\u0142o\u015bnik\u00f3w numizmatyki. Ceny peerelowskich monet i banknot\u00f3w stale rosn\u0105. Co sprawia, \u017ce pieni\u0105dze z PRL s\u0105 tak poszukiwane w ...",
            "image_url": "https://www.bing.pl/th?id=ODF.qEcc-ZyVkvSOSXNTGhpADA&pid=news&w=16&h=16&c=14&rs=2&qlt=90",
            "category": "stare+monety",
            "date": "Gazeta Pomorska on MSN8 godz.",
            "source": "Gazeta Pomorska on MSN",
            "article_content": ""
        }
    },
    {
        "method": "POST",
        "headers": {
            "Content-Type": "application/json"
        },
        "body": {
            "title": "Ten banknot 50 z\u0142otych jest wart fortun\u0119! A to nie jedyny okaz, kt\u00f3rego szukaj\u0105 kolekcjonerzy [24.04.2025]",
            "link": "https://www.msn.com/pl-pl/wiadomosci/other/ten-banknot-50-z%C5%82otych-jest-wart-fortun%C4%99-a-to-nie-jedyny-okaz-kt%C3%B3rego-szukaj%C4%85-kolekcjonerzy-24042025/ar-AA1Dttas?ocid=BingNewsVerp",
            "description": "Banknot 50 z\u0142 z 1994 roku, oznaczony seri\u0105 zast\u0119pcz\u0105 YA to najrzadszy banknot III Rzeczypospolitej. Jak informuje portal ...",
            "image_url": "https://www.bing.pl/th?id=OVF.Gt96lQRzBPXHNT2LfAnJwQ&pid=News&w=234&h=132&c=14&rs=2&qlt=30",
            "category": "stare+monety",
            "date": "Gazeta Pomorska on MSN17 godz.",
            "source": "Gazeta Pomorska on MSN",
            "article_content": ""
        }
    },
    {
        "method": "POST",
        "headers": {
            "Content-Type": "application/json"
        },
        "body": {
            "title": "Krocie za poszukiwane wazony PRL. Tyle w 2025 roku p\u0142ac\u0105 kolekcjonerzy za stare kryszta\u0142owe, porcelanowe i szklane wazony [24.04.25]",
            "link": "https://www.msn.com/pl-pl/historia-i-kultura-spo%C5%82ecze%C5%84stwa/pop-kultura/krocie-za-poszukiwane-wazony-prl-tyle-w-2025-roku-p%C5%82ac%C4%85-kolekcjonerzy-za-stare-kryszta%C5%82owe-porcelanowe-i-szklane-wazony-9-04-25-r/ar-AA1CBMeE?ocid=BingNewsVerp",
            "description": "pochodzenia - wazony z renomowanych hut, takich jak \"Z\u0105bkowice\" czy \"Irena\", s\u0105 bardziej warto\u015bciowe.",
            "image_url": "https://www.bing.pl/th?id=OVF.%2b1wZpISEwXr10vTkliI6Bg&pid=News&w=234&h=132&c=14&rs=2&qlt=30",
            "category": "stare+monety",
            "date": "Express Bydgoski on MSN8 godz.",
            "source": "Express Bydgoski on MSN",
            "article_content": ""
        }
    },
    {
        "method": "POST",
        "headers": {
            "Content-Type": "application/json"
        },
        "body": {
            "title": "Ta porcelana z PRL jest warta maj\u0105tek! Masz j\u0105 w domu? Mo\u017cesz nie\u017ale zarobi\u0107! Tej porcelany szukaj\u0105 kolekcjonerzy 24.04.2025",
            "link": "https://gk24.pl/ta-porcelana-z-prl-jest-warta-majatek-masz-ja-w-domu-mozesz-niezle-zarobic-tej-porcelany-szukaja-kolekcjonerzy-24-04-2025/ar/c9p2-27406077",
            "description": "Unikatowy charakter mia\u0142y r\u00f3wnie\u017c przedmioty z tego okresu. Z pewno\u015bci\u0105 wiele os\u00f3b posiada w swoich domach rzeczy z czas\u00f3w ...",
            "image_url": "https://www.bing.pl/th?id=OVF.s6rkLkyXtCBPL8gqvAH5Cg&pid=News&w=234&h=132&c=14&rs=2&qlt=30",
            "category": "stare+monety",
            "date": "G\u0142os Koszali\u0144ski21 godz.",
            "source": "G\u0142os Koszali\u0144ski",
            "article_content": "Content not available"
        }
    },
    {
        "method": "POST",
        "headers": {
            "Content-Type": "application/json"
        },
        "body": {
            "title": "Wazony z czas\u00f3w PRL. Od codzienno\u015bci do kolekcjonerskiego hitu. Oto wazony poszukiwane w internecie 24.04.2025",
            "link": "https://www.msn.com/pl-pl/styl-zycia/dom-i-ogrod/wazony-z-czas%C3%B3w-prl-od-codzienno%C5%9Bci-do-kolekcjonerskiego-hitu-oto-wazony-poszukiwane-w-internecie-24042025/ar-AA1xEYBt?ocid=BingNewsVerp",
            "description": "W czasach Polskiej Rzeczypospolitej Ludowej (PRL) wn\u0119trza polskich dom\u00f3w wype\u0142nia\u0142y przedmioty, kt\u00f3re dzi\u015b prze\u017cywaj\u0105 swoj\u0105 ...",
            "image_url": "https://www.bing.pl/th?id=OVFT.IL8KRDrxvOLkKrRrYKbPki&pid=News&w=234&h=132&c=14&rs=2&qlt=30",
            "category": "stare+monety",
            "date": "G\u0142os Pomorza on MSN19 godz.",
            "source": "G\u0142os Pomorza on MSN",
            "article_content": ""
        }
    },
    {
        "method": "POST",
        "headers": {
            "Content-Type": "application/json"
        },
        "body": {
            "title": "Porcelana PRL \u2013 naczynia z lat 60., 70., 80. warte fortun\u0119! Ile trzeba zap\u0142aci\u0107 w 2025 roku?",
            "link": "https://www.msn.com/pl-pl/styl-zycia/dom-i-ogrod/porcelana-prl-naczynia-z-lat-60-70-80-warte-fortun%C4%99-ile-trzeba-zap%C5%82aci%C4%87-w-2025-roku/ar-AA1Dz2Gy?ocid=BingNewsVerp",
            "description": "Stara porcelana z czas\u00f3w PRL, cieszy si\u0119 rosn\u0105cym zainteresowaniem. Niekt\u00f3re egzemplarze mog\u0105 by\u0107 dzi\u015b bardzo cenne. Takie ...",
            "image_url": "https://www.bing.pl/th?id=OVFT.L8bCDPW8GmCK7OTrAS5dyi&pid=News&w=234&h=132&c=14&rs=2&qlt=30",
            "category": "stara+porcelana",
            "date": "Nowo\u015bci Dziennik Toru\u0144ski on MSN4 godz.",
            "source": "Nowo\u015bci Dziennik Toru\u0144ski on MSN",
            "article_content": ""
        }
    },
    {
        "method": "POST",
        "headers": {
            "Content-Type": "application/json"
        },
        "body": {
            "title": "Ta porcelana z PRL jest warta maj\u0105tek! Masz j\u0105 w domu? Mo\u017cesz nie\u017ale zarobi\u0107! Tej porcelany szukaj\u0105 kolekcjonerzy 24.04.2025",
            "link": "https://gk24.pl/ta-porcelana-z-prl-jest-warta-majatek-masz-ja-w-domu-mozesz-niezle-zarobic-tej-porcelany-szukaja-kolekcjonerzy-24-04-2025/ar/c9p2-27406077",
            "description": "Unikatowy charakter mia\u0142y r\u00f3wnie\u017c przedmioty z tego okresu. Z pewno\u015bci\u0105 wiele os\u00f3b posiada w swoich domach rzeczy z czas\u00f3w ...",
            "image_url": "https://www.bing.pl/th?id=OVF.s6rkLkyXtCBPL8gqvAH5Cg&pid=News&w=234&h=132&c=14&rs=2&qlt=30",
            "category": "stara+porcelana",
            "date": "G\u0142os Koszali\u0144ski21 godz.",
            "source": "G\u0142os Koszali\u0144ski",
            "article_content": "Content not available"
        }
    },
    {
        "method": "POST",
        "headers": {
            "Content-Type": "application/json"
        },
        "body": {
            "title": "Porcelana z PRL - kolekcjonerski rarytas. Unikalne przedmioty do kupienia na aukcjach internetowych. Masz je w domu? 24.04.2025",
            "link": "https://www.msn.com/pl-pl/wiadomosci/other/porcelana-z-prl-kolekcjonerski-rarytas-unikalne-przedmioty-do-kupienia-na-aukcjach-internetowych-masz-je-w-domu-24042025/ar-AA1xHP7I?ocid=BingNewsVerp",
            "description": "Unikalna porcelana z PRL poszukiwana przez kolekcjoner\u00f3w mo\u017ce zapewni\u0107 Wam du\u017co pieni\u0119dzy. Mo\u017cemy na niej zarobi\u0107 fortun\u0119!",
            "image_url": "https://www.bing.pl/th?id=OVF.XmPGy7P2Y4xfoQzoGMTPSw&pid=News&w=234&h=132&c=14&rs=2&qlt=30",
            "category": "stara+porcelana",
            "date": "G\u0142os Pomorza on MSN19 godz.",
            "source": "G\u0142os Pomorza on MSN",
            "article_content": ""
        }
    },
    {
        "method": "POST",
        "headers": {
            "Content-Type": "application/json"
        },
        "body": {
            "title": "Historia o po\u015bwi\u0119ceniu, zdradzie, mi\u0142o\u015bci i tajemnicy. Fragment ksi\u0105\u017cki \"Ksi\u0119\u017cycowa winnica\"",
            "link": "https://www.onet.pl/kultura/dom-wydawniczy-rebis/historia-o-poswieceniu-zdradzie-milosci-i-tajemnicy-fragment-ksiazki-ksiezycowa/exrdx3c,30bc1058",
            "description": "Aldara uciek\u0142a z Hiszpanii przed wojn\u0105 domow\u0105 i w\u0142a\u015bnie zosta\u0142a \u017con\u0105 Octave\u2019a, dziedzica posiad\u0142o\u015bci. Wydawa\u0142oby si\u0119, \u017ce ...",
            "image_url": "https://www.bing.pl/th?id=OVFT.Kc6FXv9kXfGab-CR86gKmS&pid=News&w=234&h=132&c=14&rs=2&qlt=30",
            "category": "stara+porcelana",
            "date": "Onet9 godz.",
            "source": "Onet",
            "article_content": "Partner Dom Wydawniczy REBIS Ksi\u0119\u017cycowa winnica\n\nCarla Montero, autorka bestsellerowej \"Szmaragdowej tablicy\" wraca z now\u0105 powie\u015bci\u0105 pt. \"Ksi\u0119\u017cycowa winnica\". Oto jej fragment.\n\nProlog\n\nPa\u017adziernik 1943\n\nNatychmiast zauwa\u017cy\u0142, \u017ce kto\u015b otworzy\u0142 drzwi na o\u015bcie\u017c. Nie mia\u0142 w\u0105tpliwo\u015bci, \u017ce dobrze je zamkn\u0105\u0142. Pierre Brocan, dumny ma\u00eetre de chai, cz\u0142owiek z wieloletnim do\u015bwiadczeniem, nie pope\u0142nia\u0142 tak powa\u017cnych b\u0142\u0119d\u00f3w. Zlali ju\u017c moszcz z kadzi, wi\u0119c nie chcia\u0142, \u017ceby ktokolwiek wchodzi\u0142 do tej sali, dop\u00f3ki nie zostan\u0105 umyte. By\u0142o to jedno z najstarszych piwnicznych pomieszcze\u0144, dawna le\u017cakownia z bardzo w\u0105skim wej\u015bciem i pozbawiona odpowiedniej wentylacji. Resztki fermentuj\u0105cego moszczu mog\u0142y jeszcze wyprodukowa\u0107 do\u015b\u0107 dwutlenku w\u0119gla, \u017ceby wypchn\u0105\u0107 st\u0105d ca\u0142y tlen i udusi\u0107 zab\u0142\u0105kanego go\u015bcia. Niebezpiecze\u0144stwo by\u0142o jak najbardziej realne. A on traktowa\u0142 je z powag\u0105. Ktokolwiek otworzy\u0142 te drzwi, b\u0119dzie mia\u0142 z nim do czynienia.\n\nreklama\n\nPodszed\u0142 do wej\u015bcia, dla pewno\u015bci trzymaj\u0105c przed sob\u0105 zapalon\u0105 \u015bwiec\u0119. Z ulg\u0105 stwierdzi\u0142, \u017ce p\u0142omie\u0144 nie ga\u015bnie. Drzwi by\u0142y pewnie otwarte od d\u0142u\u017cszego czasu i sala zd\u0105\u017cy\u0142a si\u0119 przewietrzy\u0107. Zobaczy\u0142, \u017ce do jednej kadzi przystawiono drabin\u0119. To ju\u017c by\u0142o naprawd\u0119 dziwne. Ewidentnie kto\u015b si\u0119 tutaj kr\u0119ci\u0142. Kto m\u00f3g\u0142 by\u0107 tak lekkomy\u015blny?\n\nPrzekr\u0119ci\u0142 w\u0142\u0105cznik \u015bwiat\u0142a i z wci\u0105\u017c zapalon\u0105 \u015bwiec\u0105 wszed\u0142 do \u015brodka. W ustach mia\u0142 gorzki posmak z\u0142ego przeczucia. Nie, zdecydowanie tej drabiny nie powinno tu by\u0107. Zacz\u0105\u0142 si\u0119 wspina\u0107 po szczeblach z bij\u0105cym sercem, napi\u0119tymi mi\u0119\u015bniami i oczami wpatrzonymi w dr\u017c\u0105cy p\u0142omie\u0144. Nazywali j\u0105 s\u0142odk\u0105 \u015bmierci\u0105. W jednej chwili m\u00f3g\u0142 tam zasn\u0105\u0107 i umrze\u0107. Kiedy znalaz\u0142 si\u0119 na platformie, zajrza\u0142 do wn\u0119trza kadzi. Pocz\u0105tkowo jej dno wyda\u0142o mu si\u0119 czarn\u0105 paszcz\u0105 lwa. Stopniowo jednak wy\u0142ania\u0142 si\u0119 z niej przera\u017caj\u0105cy obraz.\n\nNa dnie kadzi le\u017ca\u0142 na plecach cz\u0142owiek, na wp\u00f3\u0142 zatopiony w lepkiej brei wyt\u0142oczyn, pestek, kryszta\u0142k\u00f3w winianu i innych pozosta\u0142o\u015bci po fermentacji. Rozpozna\u0142 jego napuchni\u0119t\u0105, niemal fioletow\u0105 twarz i mundur. Niemiecki mundur.\n\nPierre sta\u0142 w bezruchu ze wzrokiem utkwionym w cia\u0142o, zastyg\u0142y w chorobliwej fascynacji.\n\nBosz na pewno by\u0142 martwy, niewielu potrafi si\u0119 wywin\u0105\u0107 s\u0142odkiej \u015bmierci. Je\u015bli jednak pozosta\u0142o w nim cho\u0107 tchnienie \u017cycia, Pierre nie kiwnie palcem, \u017ceby go uratowa\u0107. Ten skurwiel zas\u0142u\u017cy\u0142 sobie na \u015bmier\u0107. Ma\u00eetre de chai powoli zszed\u0142 po drabinie. W tej chwili martwi\u0142 si\u0119 tylko problemami, kt\u00f3re zaraz spadn\u0105 mu na g\u0142ow\u0119. I obawia\u0142 si\u0119 konsekwencji dla winnicy. I dla madame.\n\nKrystian Daszkowski / Partner Dom Wydawniczy REBIS Ksi\u0119\u017cycowa winnica\n\n(...)\n\n\u2013 Ach, tegoroczne winobranie\u2026 M\u00f3wi\u0142em ci to ju\u017c kilka razy: natura te\u017c cierpi z naszego powodu. Czy\u017c w sumie nie jeste\u015bmy jedno\u015bci\u0105? Dlatego zbiory b\u0119d\u0105 s\u0142abe w roku, kiedy zaczyna si\u0119 wojna, i dobre, kiedy si\u0119 sko\u0144czy. Winogrona potrzebuj\u0105 jeszcze du\u017co czasu, nawet na dzia\u0142kach, gdzie zwykle dojrzewaj\u0105 najszybciej. Nie wiem, kiedy b\u0119dziemy mogli zacz\u0105\u0107 zbi\u00f3r. A poniewa\u017c mocno si\u0119 och\u0142odzi\u0142o, zaraz jesie\u0144\u2026 Nie, to nie b\u0119dzie dobry rok.\n\nOctave zmartwiony przygl\u0105da\u0142 si\u0119 ojcu. Markiz by\u0142 cz\u0142owiekiem energicznym, o imponuj\u0105cym wygl\u0105dzie i walecznym temperamencie. W tamtej chwili wygl\u0105da\u0142 jednak na przyt\u0142oczonego ci\u0119\u017carem lat i trosk. No dobrze, ale czego innego nale\u017ca\u0142o si\u0119 spodziewa\u0107 po kim\u015b, kto prze\u017cy\u0142 jedn\u0105 wyniszczaj\u0105c\u0105 wojn\u0119 i mia\u0142 \u015bwiadomo\u015b\u0107, \u017ce zaczyna si\u0119 nast\u0119pna, kt\u00f3ra nie wiadomo, jak si\u0119 sko\u0144czy?\n\nreklama\n\nM\u0142odzieniec, ze skr\u0119conym \u017co\u0142\u0105dkiem, pomy\u015bla\u0142, \u017ce okoliczno\u015bci nie s\u0105 chyba odpowiednie, by przekaza\u0107 ojcu wiadomo\u015b\u0107, z kt\u00f3r\u0105 przyszed\u0142.\n\nAuguste zobaczy\u0142, \u017ce twarz Octave\u2019a staje si\u0119 powa\u017cna i napi\u0119ta i \u017ce syn chowa r\u0119ce za plecami; zawsze tak robi\u0142, kiedy by\u0142 zdenerwowany. Markiz zmarszczy\u0142 czo\u0142o. \u2013 Ojcze\u2026 \u2013 G\u0142os Octave\u2019a by\u0142 zd\u0142awiony, jeszcze bardziej rozstrojony i dzieci\u0119cy ni\u017c zwykle. \u2013 Ja\u2026 Mam ci co\u015b wa\u017cnego do powiedzenia.\n\n\u2013\u2013\u2013\u2013 \u2022 \u2013\u2013\u2013\u2013\u2013\n\nAldara by\u0142a oszo\u0142omiona. Z nerw\u00f3w czu\u0142a md\u0142o\u015bci. Wytar\u0142a spocone d\u0142onie w sukienk\u0119 i natychmiast skarci\u0142a si\u0119 za niezr\u0119czno\u015b\u0107. Jeszcze tylko brakowa\u0142o, \u017ceby poplami\u0142a delikatn\u0105 jedwabn\u0105 taft\u0119. Na szcz\u0119\u015bcie nie znalaz\u0142a na tkaninie \u017cadnych \u015blad\u00f3w. A jednak by\u0142o oczywiste, \u017ce nie jest przyzwyczajona do noszenia czego\u015b tak wyszukanego. Wszyscy na pewno to zauwa\u017cyli. Przygl\u0105da\u0142a si\u0119 swojemu odbiciu w wisz\u0105cym nad kominkiem wielkim lustrze ze z\u0142ot\u0105 ram\u0105.\n\nUpewni\u0142a si\u0119, \u017ce ta prze\u015bliczna sukienka, szmizjerka bez r\u0119kaw\u00f3w w kolorze b\u0142\u0119kitnej porcelany, pasuje do jej oczu i podkre\u015bla opalon\u0105 sk\u00f3r\u0119 oraz ciemne w\u0142osy. I \u017ce znakomicie na niej le\u017cy, na jej wysokim, smuk\u0142ym ciele, w kt\u00f3rym zawsze brakowa\u0142o jej odrobin\u0119 obfitszego biustu i bioder jak u aktorek z ameryka\u0144skich film\u00f3w. Ta sukienka spodoba\u0142a jej si\u0119, gdy tylko zobaczy\u0142a j\u0105 na wystawie boutique w Lyonie, mie\u015bcie uznanym niegdy\u015b za \u015bwiatow\u0105 stolic\u0119 jedwabiu. I chocia\u017c straci\u0142o ju\u017c wiele z dawnego splendoru, ci\u0105gle mo\u017cna w nim by\u0142o znale\u017a\u0107 warsztaty wykonuj\u0105ce jedwabne cuda, jak ta tafta, lekko szeleszcz\u0105ca przy ka\u017cdym ruchu.\n\nCzy zauwa\u017cyli, \u017ce pierwszy raz ma na sobie tak wyszukan\u0105 sukienk\u0119?\n\nZauwa\u017cyli, \u017ce nie jest t\u0105, za kt\u00f3r\u0105 si\u0119 podaje?\n\nW tamtej chwili strachu by\u0142a przekonana, \u017ce ca\u0142a jej fa\u0142szywo\u015b\u0107 a\u017c k\u0142uje w oczy. Nie powinna by\u0142a doprowadza\u0107 tego tak daleko. To by\u0142o szale\u0144stwo. Czy to prawdziwa mi\u0142o\u015b\u0107 przes\u0142oni\u0142a jej rozum, czy jakie\u015b inne, znacznie mniej szlachetne uczucie? Na sam\u0105 my\u015bl o tym, \u017ce jednak to drugie, dopad\u0142y j\u0105 md\u0142o\u015bci. We w\u0142asnym odbiciu dostrzega\u0142a te tak ciemne zakamarki\u2026 Z westchnieniem odwr\u00f3ci\u0142a si\u0119 i podesz\u0142a do wielkiego balkonu. W salonie wszystko zosta\u0142o pomy\u015blane tak, \u017ce imponowa\u0142o bogactwem: wysokie sufity udekorowane sztukateri\u0105 i plafonami, na kt\u00f3rych umieszczono inicja\u0142y w\u0142a\u015bciciela, lampy z r\u017cni\u0119tego kryszta\u0142u, dywany z cienkiej prz\u0119dzy, meble ze szlachetnego drewna, adamaszkowe zas\u0142ony, obrazy godne muzeum\u2026\n\nreklama\n\nZ balkonu rozci\u0105ga\u0142 si\u0119 widok na ogromn\u0105 przestrze\u0144: najpierw dziedziniec wysypany \u017cwirem, nast\u0119pnie ogr\u00f3d sk\u0142adaj\u0105cy si\u0119 ze stuletnich drzew, r\u00f3wno przystrzy\u017conych krzew\u00f3w, kwietnik\u00f3w i sadzawki otoczonej pos\u0105gami. Zaraz za nim zaczyna\u0142a si\u0119 winnica: wielka po\u0142a\u0107 winnej latoro\u015bli zasadzonej w r\u00f3wnych rz\u0119dach, bujnej i obci\u0105\u017conej ki\u015b\u0107mi o tej porze roku; przypomina\u0142a ogromn\u0105, mi\u0119kk\u0105, zielon\u0105 ko\u0142dr\u0119. W g\u0142\u0119bi rysowa\u0142y si\u0119 dachy ma\u0142ych miejscowo\u015bci, w\u015br\u00f3d kt\u00f3rych wyr\u00f3\u017cnia\u0142o si\u0119 miasto Beaune, stolica burgundzkiego wina. Dalej, na horyzoncie, w ten jasny i czysty dzie\u0144 mo\u017cna by\u0142o dostrzec nawet najwy\u017csze szczyty Alp. Korzystne po\u0142o\u017cenie ch\u00e2teau na wzg\u00f3rzu pozwala\u0142o podziwia\u0107 te zapieraj\u0105ce dech w piersiach widoki.\n\nKiedy Aldara us\u0142ysza\u0142a s\u0142owo ch\u00e2teau, \"zamek\", w pierwszym odruchu przysz\u0142a jej do g\u0142owy stara \u015bredniowieczna budowla z wie\u017cami, blankami i fos\u0105. Jednak\u017ce miejsce, w kt\u00f3rym si\u0119 znalaz\u0142a, nie mia\u0142o z tym nic wsp\u00f3lnego. Przeciwnie, by\u0142a to elegancka rezydencja wzniesiona pod koniec XVIII wieku, sk\u0142adaj\u0105ca si\u0119 z g\u0142\u00f3wnego pawilonu i dw\u00f3ch skrzyde\u0142 w jasnym kolorze kontrastuj\u0105cym z ciemnymi dach\u00f3wkami, pow\u015bci\u0105gliwie ozdobiona neoklasycystycznymi detalami jak frontony nad oknami i kolumnowy portyk zwie\u0144czony szlacheckim herbem. Opr\u00f3cz pa\u0142acu, typowo francuskiego, zbudowano tu kaplic\u0119, stajnie i winiarni\u0119. Ten kompleks, w po\u0142\u0105czeniu z osiemdziesi\u0119cioma hektarami terenu, stanowi\u0142 Domaine du Clair de Lune \u2013 jeden z najwa\u017cniejszych maj\u0105tk\u00f3w C\u00f4te-d\u2019Or, wielkiego regionu znanych szeroko w \u015bwiecie win burgundzkich.\n\nPo drodze, kiedy samoch\u00f3d z podniesionym dachem mija\u0142 winnice, Aldara s\u0142ucha\u0142a o climats, grand cru, pinot noir\u2026 Wszystko to wydawa\u0142o jej si\u0119 zbyt obce i skomplikowane. Dlatego w ko\u0144cu zamkn\u0119\u0142a oczy i skupi\u0142a si\u0119 na rozkoszowaniu si\u0119 ch\u0142odnym wietrzykiem i s\u0142o\u0144cem na twarzy.\n\nreklama\n\nOczywi\u015bcie teraz w sercu tego miejsca z niepokojem zadawa\u0142a sobie pytanie, co ona tam w\u0142a\u015bciwie robi, obawia\u0142a si\u0119, \u017ce da\u0142a si\u0119 ponie\u015b\u0107 nastrojowi chwili i \u017ce zaraz wszystko zniknie jak mira\u017c \u2013 ba\u0142a si\u0119 tego od chwili, gdy min\u0119li imponuj\u0105c\u0105 bram\u0119 Domaine du Clair de Lune.\n\nZgrzyt klamki drzwi sprawi\u0142, \u017ce a\u017c podskoczy\u0142a, tak bardzo mia\u0142a napi\u0119te nerwy. Odwr\u00f3ci\u0142a si\u0119.\n\n\u2013 Aldaro\u2026\n\nOctave, u\u015bmiechaj\u0105c si\u0119 r\u00f3wnie sztucznie jak ona, podszed\u0142 i delikatnie uj\u0105\u0142 j\u0105 za r\u0119k\u0119. Dziewczyna patrzy\u0142a jednak ponad ramieniem Octave\u2019a na eleganckiego m\u0119\u017cczyzn\u0119 o szpakowatych, przerzedzonych, g\u0142adko zaczesanych w\u0142osach. Jego zaci\u015bni\u0119te usta zdawa\u0142y si\u0119 nikn\u0105\u0107 pod cienkimi czarnymi w\u0105sami, a wielkie jasne oczy wpatrywa\u0142y si\u0119 w ni\u0105 \u015bwidruj\u0105co; w sumie wyraz jego twarzy w \u017cadnym razie nie wyda\u0142 jej si\u0119 mi\u0142y. Mia\u0142 na sobie trzycz\u0119\u015bciowy garnitur, wykrochmalon\u0105 koszul\u0119 i krawat; dewizka zegarka l\u015bni\u0142a na szarym materiale ubrania.\n\nPoprowadzona przez Octave\u2019a podesz\u0142a do m\u0119\u017cczyzny. Prze\u0142kn\u0119\u0142a \u015blin\u0119. Stara\u0142a si\u0119 u\u015bmiecha\u0107.\n\n\u2013 Ojcze, przedstawiam ci Aldar\u0119 Saur\u00ed. Moj\u0105 \u017con\u0119.\n\nAldara wyci\u0105gn\u0119\u0142a r\u0119k\u0119, maj\u0105c nadziej\u0119, \u017ce nie b\u0119dzie wida\u0107, jak si\u0119 trz\u0119sie.\n\n\u2013 Bardzo mi mi\u0142o w ko\u0144cu pana pozna\u0107, panie markizie \u2013 przywita\u0142a si\u0119 doskona\u0142\u0105 francuszczyzn\u0105.\n\nM\u0119\u017cczyzna szybko u\u015bcisn\u0105\u0142 jej d\u0142o\u0144, ale nie odezwa\u0142 si\u0119 ani s\u0142owem, wyraz jego twarzy pozosta\u0142 niezmieniony.\n\n\u2013 Cho\u0107 teraz powinienem powiedzie\u0107 Aldara de Fonneuve, prawda? Nie mog\u0119 si\u0119 przyzwyczai\u0107. \u2013 Octave za\u015bmia\u0142 si\u0119 kr\u00f3tko i nerwowo, co zabrzmia\u0142o jak zgrzyt metalu.\n\nJego nieudolna pr\u00f3ba rozlu\u017anienia atmosfery spe\u0142z\u0142a na niczym.\n\nAldara poczu\u0142a, \u017ce markiz, ci\u0105gle milcz\u0105cy, wpatruje si\u0119 w ni\u0105, jakby chcia\u0142 j\u0105 przejrze\u0107 na wylot, jakby chcia\u0142 pozna\u0107 jej przesz\u0142o\u015b\u0107 i odszyfrowa\u0107 jej intencje, zanim zdo\u0142a go oszuka\u0107. W ko\u0144cu, jak zawsze wszyscy, zatrzyma\u0142 si\u0119 na jej bli\u017anie \u2013 szramie przebiegaj\u0105cej od k\u0105cika ust do ucha.\n\nreklama\n\n\u2013 Sk\u0105d ma pani t\u0119 blizn\u0119? \u2013 G\u0142os markiza zabrzmia\u0142 tubalnie i g\u0142\u0119boko, jak g\u0142os ogra.\n\nOctave odchrz\u0105kn\u0105\u0142, jakby pr\u00f3bowa\u0142 st\u0142umi\u0107 niepok\u00f3j. \u015acisn\u0105\u0142 r\u0119k\u0119 ma\u0142\u017conki. Chcia\u0142 stan\u0105\u0107 w jej obronie, ale kiedy zbiera\u0142 na to odwag\u0119, Aldara bez wahania odpowiedzia\u0142a: \u2013 Zbombardowano nasz samoch\u00f3d, kiedy jechali\u015bmy do granicy. Siedzia\u0142am przy oknie i kawa\u0142ek szk\u0142a rozci\u0105\u0142 mi twarz.\n\n\u2013 Aldara jest Hiszpank\u0105. Przyjecha\u0142a do Francji, uciekaj\u0105c przed wojn\u0105 domow\u0105\n\n\u2013 Octave po\u015bpieszy\u0142 z wyja\u015bnieniem.\n\nMimo nalega\u0144 ojca podczas kr\u00f3tkiej drogi z winiarni do domu nie pisn\u0105\u0142 s\u0142\u00f3wkiem na temat niespodzianki, kt\u00f3r\u0105 dla niego przygotowa\u0142. Ani o tym, \u017ce w salonie czeka kobieta b\u0119d\u0105ca jego \u017con\u0105, ani kim ona jest, ani w jakich okoliczno\u015bciach zawarli to pospieszne ma\u0142\u017ce\u0144stwo. Octave uzna\u0142, \u017ce lepiej zaskoczy\u0107 ojca; prawda jednak by\u0142a taka, \u017ce umiera\u0142 ze strachu, wi\u0119c doszed\u0142 do wniosku, \u017ce je\u015bli zrzuci bomb\u0119 w obecno\u015bci Aldary, markiz nie b\u0119dzie robi\u0142 scen i wszystko p\u00f3jdzie \u0142atwiej. Jak\u017ce si\u0119 myli\u0142!\n\nAuguste spojrza\u0142 na niego twardo.\n\n\u2013 Octave, musz\u0119 z tob\u0105 porozmawia\u0107. Na osobno\u015bci.\n\nCh\u0142opak skin\u0105\u0142 g\u0142ow\u0105 i zwr\u00f3ci\u0142 si\u0119 do ma\u0142\u017conki:\n\n\u2013 Wybacz. Zaraz wr\u00f3c\u0119\u2026\n\nMia\u0142by ochot\u0119 j\u0105 przytuli\u0107, poprosi\u0107, \u017ceby si\u0119 nie martwi\u0142a, bo wszystko si\u0119 u\u0142o\u017cy, gdy\u017c ojciec, cho\u0107 surowy i zaskoczony wiadomo\u015bci\u0105, jest dobrym cz\u0142owiekiem. Chcia\u0142by j\u0105 poca\u0142owa\u0107 i powiedzie\u0107, \u017ce j\u0105 kocha. Przyt\u0142oczony postaw\u0105 ojca ograniczy\u0142 si\u0119 jednak do pog\u0142askania jej d\u0142oni, po czym pu\u015bci\u0142 j\u0105 i wyszed\u0142 z salonu eskortowany przez markiza jak wi\u0119zie\u0144.\n\nZostawszy sama, Aldara poczu\u0142a, \u017ce mi\u0119kn\u0105 jej nogi, wi\u0119c przysiad\u0142a na krze\u015ble. Ukry\u0142a twarz w d\u0142oniach. Pope\u0142ni\u0142a wielki b\u0142\u0105d, wychodz\u0105c za Octave\u2019a. Nie nale\u017ca\u0142a do tego miejsca ani do tego \u015brodowiska. Wszystko w niej by\u0142o k\u0142amstwem, kt\u00f3re szybko zostanie odkryte. Co si\u0119 wtedy wydarzy? Ta mimowolna przygoda nie mog\u0142a sko\u0144czy\u0107 si\u0119 dobrze ani dla niej, ani dla niego. A do tego ju\u017c za chwil\u0119 mia\u0142a ich rozdzieli\u0107 wojna.\n\nreklama\n\nUnios\u0142a zaczerwienion\u0105 twarz i spojrza\u0142a na drzwi. Czy zd\u0105\u017cy wyj\u015b\u0107 i wycofa\u0107 si\u0119 po swoich \u015bladach? Czy zd\u0105\u017cy naprawi\u0107 g\u0142upstwo, kt\u00f3re pope\u0142ni\u0142a?\n\nPowy\u017cszy fragment pochodzi z najnowszej powie\u015bci Carli Montero pt. \"Ksi\u0119\u017cycowa winnica\". Ksi\u0105\u017cka od 22 kwietnia dost\u0119pna w ksi\u0119garniach!\n\nCarla Montero, hiszpa\u0144ska pisarka, jest absolwentk\u0105 prawa i zarz\u0105dzania w biznesie, od zawsze jednak uwielbia\u0142a pisa\u0107. Jej debiutancka powie\u015b\u0107 \"Wiede\u0144ska gra\" otrzyma\u0142a nagrod\u0119 C\u00edrculo de Lectores; \"Szmaragdowa tablica\" zosta\u0142a bestsellerem tak\u017ce w Polsce \u2013 opr\u00f3cz nich REBIS opublikowa\u0142 r\u00f3wnie\u017c powie\u015bci Montero \"Z\u0142ota sk\u00f3ra\", \"Zimowy wiatr na twojej twarzy\" i \"Ogr\u00f3d kobiet\". Pisarzem jest te\u017c brat Carli \u2013 Luis Montero Manglano, autor wydanej przez REBIS trylogii \"Poszukiwacze\"."
        }
    },
    {
        "method": "POST",
        "headers": {
            "Content-Type": "application/json"
        },
        "body": {
            "title": "Przegl\u0105d prasy (24.04.2025). Zobacz pras\u00f3wk\u0119 z najwa\u017cniejszymi wydarzeniami z wczoraj. B\u0105d\u017a na bie\u017c\u0105co",
            "link": "https://kurierlubelski.pl/przeglad-prasy-24-04-2025-zobacz-prasowke-z-najwazniejszymi-wydarzeniami-z-wczoraj-badz-na-biezaco/ar/c1p1-19960905",
            "description": "Przed siatkarzami Bogdanki LUK Lublin ostatni mecz fazy zasadniczej. \u017b\u00f3\u0142to-czarni w 30. kolejce PlusLigi podejm\u0105 w ...",
            "image_url": "https://www.bing.pl/th?id=OVFT.MSuvYHc7hmb0aRLfQwelKC&pid=News&w=234&h=132&c=14&rs=2&qlt=30",
            "category": "stara+porcelana",
            "date": "Kurier Lubelski21 godz.",
            "source": "Kurier Lubelski",
            "article_content": "Content not available"
        }
    },
    {
        "method": "POST",
        "headers": {
            "Content-Type": "application/json"
        },
        "body": {
            "title": "Kolejny Rozwadowski Targ Staroci w Stalowej Woli odb\u0119dzie si\u0119 w niedziel\u0119, 27 kwietnia",
            "link": "https://echodnia.eu/podkarpackie/kolejny-rozwadowski-targ-staroci-w-stalowej-woli-odbedzie-sie-w-niedziele-27-kwietnia/ar/c1p2-27500961",
            "description": "Lucjusz Nadbere\u017cny Prezydent Miasta Stalowej Woli zaprasza wszystkich na Targ Staroci w godzinach od 7.00 do 13.00 na Rynek w Rozwadowie, by podzieli\u0107 si\u0119 swoimi unikatowymi znaleziskami oraz odkry\u0107 ...",
            "image_url": "https://www.bing.pl/th?id=ODF.xmtGTJHQSE_v4D-CWxbvsQ&pid=news&w=16&h=16&c=14&rs=2&qlt=90",
            "category": "targ+staroci",
            "date": "Echo Dnia10 godz.",
            "source": "Echo Dnia",
            "article_content": "Content not available"
        }
    },
    {
        "method": "POST",
        "headers": {
            "Content-Type": "application/json"
        },
        "body": {
            "title": "Festiwal Tulipan\u00f3w w Ogrodzie Botanicznym",
            "link": "https://www.msn.com/pl-pl/rozrywka/news/weekend-we-wroc%C5%82awiu-25-2704-koncerty-pod-gwiazdami-targi-vintage-biegi-rodzinne-i-spektakle-kwiatowe-nie-przegap-wyj%C4%85tkowych-wydarze%C5%84/ar-AA1DyJfU?ocid=BingNewsVerp",
            "description": "Kultowe melodie z sagi w wykonaniu fortepianu i kwartetu smyczkowego. Koncert w Sali Radia Wroc\u0142aw przeniesie s\u0142uchaczy w ...",
            "image_url": "https://www.bing.pl/th?id=OVF.6x0zI0nV1RM1NNbaCKzGXA&pid=News&w=234&h=132&c=14&rs=2&qlt=30",
            "category": "targ+staroci",
            "date": "Wroc\u0142aw Nasze Miasto on MSN5 godz.",
            "source": "Wroc\u0142aw Nasze Miasto on MSN",
            "article_content": ""
        }
    },
    {
        "method": "POST",
        "headers": {
            "Content-Type": "application/json"
        },
        "body": {
            "title": "Kolekcjonerzy poszukuj\u0105 tych antyk\u00f3w. Unikalne przedmioty do kupienia w internecie. Masz je w domu? 24.04.2025",
            "link": "https://dziennikbaltycki.pl/kolekcjonerzy-poszukuja-tych-antykow-unikalne-przedmioty-do-kupienia-w-internecie-masz-je-w-domu-24042025/ar/c9-17262255",
            "description": "Unikalne antyki poszukiwane przez kolekcjoner\u00f3w mog\u0105 zapewni\u0107 Wam du\u017co pieni\u0119dzy. Mo\u017cemy na nich zarobi\u0107 fortun\u0119. Cz\u0119sto nie ...",
            "image_url": "https://www.bing.pl/th?id=OVF.rpbquUdeFwPO%2bLSCr9SN2Q&pid=News&w=234&h=132&c=14&rs=2&qlt=30",
            "category": "targ+staroci",
            "date": "Dziennik Ba\u0142tycki19 godz.",
            "source": "Dziennik Ba\u0142tycki",
            "article_content": "Content not available"
        }
    },
    {
        "method": "POST",
        "headers": {
            "Content-Type": "application/json"
        },
        "body": {
            "title": "Suska Maj\u00f3wka - co w programie?",
            "link": "https://sucha24.pl/artykul/suska-majowka--co-w-n1577253",
            "description": "Suska Maj\u00f3wka na sta\u0142e wpisa\u0142a si\u0119 w kalendarz miejskich imprez sportowych i rozrywkowych. Tegoroczna edycja potrwa cztery ...",
            "image_url": "https://www.bing.pl/th?id=OVFT.qfN_GYFWOlukoq5PHiymvC&pid=News&w=234&h=132&c=14&rs=2&qlt=30",
            "category": "targ+staroci",
            "date": "Sucha2418 godz.",
            "source": "Sucha24",
            "article_content": "Suska Maj\u00f3wka na sta\u0142e wpisa\u0142a si\u0119 w kalendarz miejskich imprez sportowych i rozrywkowych. Tegoroczna edycja potrwa cztery dni i rozpocznie si\u0119 1 maja. Jak co roku b\u0119dzie obfitowa\u0107 w wydarzenia sportowe i kulturalne, dzi\u0119ki czemu ka\u017cdy z pewno\u015bci\u0105 znajdzie co\u015b dla siebie.\n\nSta\u0142o si\u0119 ju\u017c niepisan\u0105 tradycj\u0105, \u017ce wydarzeniem otwieraj\u0105cym Susk\u0105 Maj\u00f3wk\u0119 s\u0105 Targi Kwiatowe na miejskim placu targowym \u2013 kontynuacja dawnej Wystawy Ogrodniczej. Co roku ciesz\u0105 si\u0119 one ogromnym zainteresowaniem ze strony wystawc\u00f3w i odwiedzaj\u0105cych. Tegoroczne Targi rozpoczn\u0105 si\u0119 o godz. 6:00, a odwiedzaj\u0105cy b\u0119d\u0105 mieli niepowtarzaln\u0105 okazj\u0119 zakupu w jednym miejscu kwiat\u00f3w, drzewek, krzew\u00f3w, iglak\u00f3w, rozsad, nasion, a tak\u017ce narz\u0119dzi ogrodniczych, ozd\u00f3b oraz wyrob\u00f3w z wikliny.\n\nW czwartkowe przedpo\u0142udnie zapraszamy r\u00f3wnie\u017c na wernisa\u017c 19. Wystawy \u015arodowiskowej w Galerii Sztuki \u2013 Zamek oraz do udzia\u0142u w jubileuszowych, X Otwartych Mistrzostwach Suchej Beskidzkiej w Scrabble, kt\u00f3rych organizatorem jest Biblioteka Suska. Zar\u00f3wno przed po\u0142udniem, jak i po po\u0142udniu, nie zabraknie emocji sportowych. O poranku na basenie odb\u0119dzie si\u0119 pokaz umiej\u0119tno\u015bci p\u0142ywackich, a kilka godzin p\u00f3\u017aniej na stadionie sportowym \u2013 zawody biegowe dla dzieci. Po nich, na Orliku, rywalizowa\u0107 b\u0119d\u0105 uczestnicy Turnieju Pi\u0142ki No\u017cnej Zak\u0142ad\u00f3w Pracy.\n\nSportowych wra\u017ce\u0144 nie zabraknie r\u00f3wnie\u017c 2 maja. Przed po\u0142udniem (o godz. 11:00) na stadionie miejskim odb\u0119dzie si\u0119 Rajd Rowerowy dla dzieci do 12. roku \u017cycia. Godzin\u0119 wcze\u015bniej, w parku zamkowym \u2013 na tle Ma\u0142ego Wawelu \u2013 do rywalizacji stan\u0105 m\u0142odzi \u0142ucznicy. Tego dnia polecamy r\u00f3wnie\u017c warsztaty plastyczne \u201eSta\u0144 si\u0119 smokiem!\u201d, przygotowane przez Muzeum Miejskie Suchej Beskidzkiej, skierowane do dzieci w wieku od 8 do 11 lat.\n\nW sobotnie przedpo\u0142udnie (3 maja) b\u0119dzie mo\u017cna sprawdzi\u0107 swoje umiej\u0119tno\u015bci w Otwartych Zawodach Strzeleckich o Puchar Burmistrza Miasta Sucha Beskidzka, kt\u00f3re rozegrane zostan\u0105 na strzelnicy LOK przy ul. Makowskiej. Mi\u0142o\u015bnik\u00f3w muzyki zapraszamy wieczorem do sali widowiskowej Centrum Kultury i Filmu na koncert muzyki francuskiej, z kt\u00f3rym wyst\u0105pi uczestnik programu \u201eMam Talent\u201d \u2013 polsko-francuski piosenkarz Francois.\n\nZwie\u0144czeniem Suskiej Maj\u00f3wki b\u0119dzie niedzielny Zamkowy Jarmark Staroci, na kt\u00f3rym z pewno\u015bci\u0105 nie zabraknie unikalnych i kolekcjonerskich przedmiot\u00f3w."
        }
    },
    {
        "method": "POST",
        "headers": {
            "Content-Type": "application/json"
        },
        "body": {
            "title": "Przegl\u0105d prasy 24.04.2025. Przygotowali\u015bmy zestaw najwa\u017cniejszych informacji z wczoraj. B\u0105d\u017a na bie\u017c\u0105co z wydarzeniami",
            "link": "https://gazetawroclawska.pl/przeglad-prasy-24-04-2025-przygotowalismy-zestaw-najwazniejszych-informacji-z-wczoraj-badz-na-biezaco-z-wydarzeniami/ar/c1p1-19960895",
            "description": "Przysz\u0142a wiosna, a Wroc\u0142aw zn\u00f3w jest pe\u0142en weekendowych atrakcji. Nadchodz\u0105ce dni wolne to prawdziwa gratka dla mieszka\u0144c\u00f3w i ...",
            "image_url": "https://www.bing.pl/th?id=OVFT.5RGrE5_om2QW9ZypI6i2Cy&pid=News&w=234&h=132&c=14&rs=2&qlt=30",
            "category": "targ+staroci",
            "date": "Gazeta Wroc\u0142awska21 godz.",
            "source": "Gazeta Wroc\u0142awska",
            "article_content": "Content not available"
        }
    },
    {
        "method": "POST",
        "headers": {
            "Content-Type": "application/json"
        },
        "body": {
            "title": "SZUKASZ: strims top wykop",
            "link": "https://niezalezna.pl/wyszukiwarka?page=18&q=strims%20top%20wykop",
            "description": "Ma\u0142a lawina \u015bnie\u017cna, kt\u00f3ra zesz\u0142a w \u015brod\u0119 ze zboczy Koziego Wierchu w Tatrach, porwa\u0142a dw\u00f3ch m\u0119\u017cczyzn. Poszkodowani nie ...",
            "image_url": "https://www.bing.pl/th?id=OVFT.ro3EUsp7ud_CGxp61kk1cy&pid=News&w=234&h=132&c=14&rs=2&qlt=30",
            "category": "relikty",
            "date": "Niezale\u017cna.pl21 godz.",
            "source": "Niezale\u017cna.pl",
            "article_content": "Content not available"
        }
    },
    {
        "method": "POST",
        "headers": {
            "Content-Type": "application/json"
        },
        "body": {
            "title": "Odkryli\u015bmy pierwsz\u0105 ciemn\u0105 galaktyk\u0119 w naszym kosmicznym s\u0105siedztwie - twierdz\u0105 chi\u0144scy astronomowie",
            "link": "https://wyborcza.pl/7,75400,31878813,odkrylismy-pierwsza-ciemna-galaktyke-w-naszym-kosmicznym-sasiedztwie.html",
            "description": "Nie ma w niej \u017cadnych gwiazd, tworzy j\u0105 wiruj\u0105cy ob\u0142ok wodoru i ciemnej materii. Modele kosmologiczne przewiduj\u0105, \u017ce takich ...",
            "image_url": "https://www.bing.pl/th?id=OVFT.0RdC7X8zvgKCWGzwymPMfi&pid=News&w=234&h=132&c=14&rs=2&qlt=30",
            "category": "relikty",
            "date": "Gazeta Wyborcza18 godz.",
            "source": "Gazeta Wyborcza",
            "article_content": ""
        }
    },
    {
        "method": "POST",
        "headers": {
            "Content-Type": "application/json"
        },
        "body": {
            "title": "Mapa schron\u00f3w w Polsce. Tutaj znajdziesz kryj\u00f3wki na wypadek wojny lub kataklizmu",
            "link": "https://www.msn.com/pl-pl/bezpiecze%C5%84stwo-publiczne-i-sytuacje-kryzysowe/ostrze%C5%BCenia-dotycz%C4%85ce-zdrowia-i-bezpiecze%C5%84stwa/mapa-schron%C3%B3w-w-polsce-tutaj-znajdziesz-kryj%C3%B3wki-na-wypadek-wojny-lub-kataklizmu/ar-AA1DxLO7?ocid=BingNewsVerp",
            "description": "Gdzie jest najbli\u017cszy schron? Takie pytanie pewnie zadawali sobie ju\u017c wszyscy. Z pomoc\u0105 przychodz\u0105 stra\u017cacy, kt\u00f3rzy ...",
            "image_url": "https://www.bing.pl/th?id=OVFT.8KdUStvRXUge8JGjQ-0snS&pid=News&w=234&h=132&c=14&rs=2&qlt=30",
            "category": "relikty",
            "date": "naTemat.pl on MSN10 godz.",
            "source": "naTemat.pl on MSN",
            "article_content": ""
        }
    },
    {
        "method": "POST",
        "headers": {
            "Content-Type": "application/json"
        },
        "body": {
            "title": "Trasy nordic walking do 69 km od Koszalina. Urocze miejsca na kr\u00f3tk\u0105 tras\u0119 w weekend 26 - 27 kwietnia",
            "link": "https://koszalin.naszemiasto.pl/trasy-nordic-walking-do-69-km-od-koszalina-urocze-miejsca-na-krotka-trase-w-weekend-26-27-kwietnia/ar/c7p1-22318903",
            "description": "Szukasz nowych \u015bcie\u017cek nordic walking w okolicy Koszalina? Razem z Traseo mamy dla Ciebie gar\u015b\u0107 pomys\u0142\u00f3w na ten tydzie\u0144.",
            "image_url": "https://www.bing.pl/th?id=OVFT.-UGQ3npGp3lWos2z4uOggS&pid=News&w=234&h=132&c=14&rs=2&qlt=30",
            "category": "relikty",
            "date": "Koszalin Nasze Miasto11 godz.",
            "source": "Koszalin Nasze Miasto",
            "article_content": "Content not available"
        }
    },
    {
        "method": "POST",
        "headers": {
            "Content-Type": "application/json"
        },
        "body": {
            "title": "Ciekawe trasy do spacerowania w woj. zachodniopomorskim. Gdzie warto i\u015b\u0107 w weekend 26 - 27 kwietnia? TOP 10 tras",
            "link": "https://gs24.pl/ciekawe-trasy-do-spacerowania-w-woj-zachodniopomorskim-gdzie-warto-isc-w-weekend-26-27-kwietnia-top-10-tras/ar/c7p1-22116477",
            "description": "W woj. zachodniopomorskim jest mn\u00f3stwo ciekawych miejsc na spacer. Mamy dla Was 10 propozycji. Mo\u017cecie nam\u00f3wi\u0107 przyjaci\u00f3\u0142 i ...",
            "image_url": "https://www.bing.pl/th?id=OVFT.bNN3Rd8BU0XN1WmcpvcpgS&pid=News&w=234&h=132&c=14&rs=2&qlt=30",
            "category": "relikty",
            "date": "G\u0142os Szczeci\u0144ski11 godz.",
            "source": "G\u0142os Szczeci\u0144ski",
            "article_content": "Content not available"
        }
    },
    {
        "method": "POST",
        "headers": {
            "Content-Type": "application/json"
        },
        "body": {
            "title": "Jak zaplanowa\u0107 city break, aby unikn\u0105\u0107 stresu i cieszy\u0107 si\u0119 atrakcjami?",
            "link": "https://www.msn.com/pl-pl/styl-zycia/moda-i-uroda/jak-zaplanowa%C4%87-city-break-aby-unikn%C4%85%C4%87-stresu-i-cieszy%C4%87-si%C4%99-atrakcjami/ar-AA1Dz6fG?ocid=BingNewsVerp",
            "description": "City break to coraz popularniejszy spos\u00f3b na oderwanie si\u0119 od codzienno\u015bci, na\u0142adowanie baterii i szybkie poznanie nowych ...",
            "image_url": "https://www.bing.pl/th?id=OVF.%2f48pLh28eTt%2bHiA5hWiR4A&pid=News&w=234&h=132&c=14&rs=2&qlt=30",
            "category": "zabytkowe+przedmioty",
            "date": "Toru\u0144 Nasze Miasto on MSN3 godz.",
            "source": "Toru\u0144 Nasze Miasto on MSN",
            "article_content": ""
        }
    },
    {
        "method": "POST",
        "headers": {
            "Content-Type": "application/json"
        },
        "body": {
            "title": "Tak tury\u015bci bawi\u0105 si\u0119 Krakowie. Odwiedzaj\u0105 miasto nie tylko dla zabytk\u00f3w - \u015bwietnie czuj\u0105 si\u0119 w polskich klubach",
            "link": "https://www.msn.com/pl-pl/rozrywka/news/tak-tury%C5%9Bci-bawi%C4%85-si%C4%99-krakowie-odwiedzaj%C4%85-miasto-nie-tylko-dla-zabytk%C3%B3w-%C5%9Bwietnie-czuj%C4%85-si%C4%99-w-polskich-klubach/ar-AA1Dx8dP?ocid=BingNewsVerp",
            "description": "Zabytkowy klimat Krakowa, nocne \u017cycie i niezapomniana atmosfera przyci\u0105gaj\u0105 co roku t\u0142umy turyst\u00f3w z ca\u0142ego \u015bwiata. A kiedy ...",
            "image_url": "https://www.bing.pl/th?id=OVF.qz9FNdZ%2b6S86cCXHGGWWhA&pid=News&w=234&h=132&c=14&rs=2&qlt=30",
            "category": "zabytkowe+przedmioty",
            "date": "Krak\u00f3w Nasze Miasto on MSN13 godz.",
            "source": "Krak\u00f3w Nasze Miasto on MSN",
            "article_content": ""
        }
    },
    {
        "method": "POST",
        "headers": {
            "Content-Type": "application/json"
        },
        "body": {
            "title": "Hydropolis we Wroc\u0142awiu \u015bwi\u0119tuje w tym roku swoje 10. urodziny. Zwiedzaj\u0105cych czeka mn\u00f3stwo atrakcji i nowo\u015bci. Oto szczeg\u00f3\u0142y",
            "link": "https://www.msn.com/pl-pl/wiadomosci/polska/hydropolis-we-wroc%C5%82awiu-%C5%9Bwi%C4%99tuje-w-tym-roku-swoje-10-urodziny-zwiedzaj%C4%85cych-czeka-mn%C3%B3stwo-atrakcji-i-nowo%C5%9Bci-oto-szczeg%C3%B3%C5%82y/ar-AA1DyuMs?ocid=BingNewsVerp",
            "description": "Hydropolis - centrum wiedzy o wodzie - to jedna z najpopularniejszych atrakcji turystycznych we Wroc\u0142awiu. Przez dekad\u0119 ...",
            "image_url": "https://www.bing.pl/th?id=OVF.o%2fW14VClFBl1hZKJwVUkjg&pid=News&w=234&h=132&c=14&rs=2&qlt=30",
            "category": "zabytkowe+przedmioty",
            "date": "Gazeta Wroc\u0142awska on MSN7 godz.",
            "source": "Gazeta Wroc\u0142awska on MSN",
            "article_content": ""
        }
    },
    {
        "method": "POST",
        "headers": {
            "Content-Type": "application/json"
        },
        "body": {
            "title": "Tak kradn\u0105 we W\u0142oszech. Polscy tury\u015bci padli ofiar\u0105 perfidnego procederu",
            "link": "https://www.fakt.pl/hobby/turystyka/plaga-kradziezy-w-turystycznym-raju-problemem-sa-nie-tylko-zlodzieje-ale-i-policja/91yfky2",
            "description": "Podr\u00f3\u017c do W\u0142och to marzenie wielu Polak\u00f3w. Malownicze wybrze\u017ca, staro\u017cytne zabytki i wy\u015bmienite jedzenie kusz\u0105 nawet ...",
            "image_url": "https://www.bing.pl/th?id=OVFT.2-18yjQSnGzdP9TAELd96C&pid=News&w=234&h=132&c=14&rs=2&qlt=30",
            "category": "zabytkowe+przedmioty",
            "date": "Fakt.pl12 godz.",
            "source": "Fakt.pl",
            "article_content": "Podr\u00f3\u017c do W\u0142och to marzenie wielu Polak\u00f3w. Malownicze wybrze\u017ca, staro\u017cytne zabytki i wy\u015bmienite jedzenie kusz\u0105 nawet najwi\u0119kszych kanapowc\u00f3w. Jednak szcz\u0119\u015bliwcy, kt\u00f3rym dany by\u0142 odpoczynek w s\u0142onecznej Italii, nie zawsze wracaj\u0105 z pi\u0119knymi wspomnieniami. W\u0142osi od lat zmagaj\u0105 si\u0119 z plag\u0105 kradzie\u017cy, a w\u015br\u00f3d poszkodowanych jest wielu turyst\u00f3w. O brawurze z\u0142odziei i bezradno\u015bci w\u0142oskiej policji opowiadaj\u0105 czytelnicy \"Faktu\". Podczas w\u0142oskich wakacji stracili nie tylko dobytek, ale r\u00f3wnie\u017c poczucie bezpiecze\u0144stwa.\n\nW\u0142ochy nale\u017c\u0105 do najcz\u0119\u015bciej odwiedzanych pa\u0144stw w Europie, w ubieg\u0142ym roku przyj\u0119\u0142y rekordowe 65 mln zagranicznych turyst\u00f3w. Ta osza\u0142amiaj\u0105ca popularno\u015b\u0107 w\u0142oskiego buta sprawia, \u017ce miasta, pla\u017ce i atrakcyjne szlaki turystyczne wprost p\u0119kaj\u0105 w szwach. A t\u0142ok przyci\u0105ga z\u0142odziei. Polskie Ministerstwo Spraw Zagranicznych ostrzega osoby wybieraj\u0105ce si\u0119 do W\u0142och przed kieszonkowcami oraz w\u0142amaniami do pojazd\u00f3w, co sta\u0142o si\u0119 prawdziw\u0105 zmor\u0105 zmotoryzowanych turyst\u00f3w. O tym, jak wygl\u0105daj\u0105 takie kradzie\u017ce, opowiedzieli nam poszkodowani czytelnicy.\n\nKradzie\u017ce we W\u0142oszech \u2013 wybita szyba i zdemolowane auto\n\nWe W\u0142oszech roi si\u0119 od kieszonkowc\u00f3w, jednak te najbardziej zuchwa\u0142e kradzie\u017ce zdarzaj\u0105 si\u0119 zwykle na parkingach, zw\u0142aszcza tych usytuowanych w pobli\u017cu pla\u017c czy turystycznych atrakcji. W zaparkowanych autach tury\u015bci cz\u0119sto zostawiaj\u0105 ca\u0142y sw\u00f3j wakacyjny dobytek. Gdy wracaj\u0105 z wycieczki, zastaj\u0105 wybite okno i ogo\u0142ocony z walizek baga\u017cnik. Do\u015bwiadczy\u0142 tego nasz czytelnik, kt\u00f3ry wypoczywa\u0142 na Sycylii. Tu\u017c przed wylotem mia\u0142 jeszcze troch\u0119 czasu, postanowi\u0142 wi\u0119c wraz z rodzin\u0105 zrelaksowa\u0107 si\u0119 na pla\u017cy.\n\n\u2013 Specjalnie wybrali\u015bmy miejsce, gdzie by\u0142o sporo ludzi i samochod\u00f3w, by unikn\u0105\u0107 sytuacji, \u017ce nasz wypo\u017cyczony samoch\u00f3d b\u0119dzie jedynym w okolicy i wystawionym na widok. Przy pla\u017cy by\u0142 du\u017cy parking, na kt\u00f3rym by\u0142o kilkana\u015bcie aut. Doko\u0142a kr\u0119ci\u0142o si\u0119 sporo pla\u017cowicz\u00f3w. I chyba to nas zmyli\u0142o \u2013 relacjonuje poszkodowany turysta. \u015awiadomy zagro\u017cenia, zadba\u0142 o to, by \"wtopi\u0107\" samoch\u00f3d w t\u0142um innych aut. Niestety, i to nie pomog\u0142o. \u2013 Na pla\u017cy sp\u0119dzili\u015bmy ok. dw\u00f3ch godzin. W pewnym momencie wr\u00f3ci\u0142em do samochodu po jakie\u015b rzeczy dla dzieci. Wtedy wszystko by\u0142o jeszcze OK. Jednak 15 minut p\u00f3\u017aniej mieli\u015bmy ju\u017c wybit\u0105 szyb\u0119 i spl\u0105drowane auto.\n\nOkaza\u0142o si\u0119, \u017ce z\u0142odzieje przez wybit\u0105 szyb\u0119 otworzyli tylne drzwi auta, a nast\u0119pnie przez opuszczone siedzenia dostali si\u0119 do baga\u017cnika. Z relacji czytelnika wynika, \u017ce ukradli wszystko, co zdo\u0142ali zabra\u0107 \u2013 torby, plecaki, nawet reklam\u00f3wk\u0119 z mokrymi butami. Zostawili tylko w\u00f3zek, kt\u00f3rego nie da\u0142o si\u0119 wyj\u0105\u0107. \u2013 Stracili\u015bmy w zasadzie wszystkie ubrania, rzeczy osobiste, kosmetyki, pami\u0105tki. Wszystko, co by\u0142o ju\u017c spakowane przed powrotem do Polski \u2013 podsumowuje pechowy turysta.\n\nJednak tym, co go najbardziej zmartwi\u0142o, by\u0142a utrata dzieci\u0119cych drobiazg\u00f3w. Chodzi\u0142o o rzeczy bezwarto\u015bciowe, ale dla maluch\u00f3w stanowi\u0142y one prawdziwy skarb. \u2013 Dzieciaki, gdy zobaczy\u0142y wybit\u0105 szyb\u0119, nie od razu zrozumia\u0142y co si\u0119 sta\u0142o. Ale ich poczucie bezpiecze\u0144stwa zosta\u0142o zmia\u017cd\u017cone dos\u0142ownie w sekund\u0119. \"Tatusiu, a zabrali te\u017c m\u00f3j kocy\u015b i lal\u0119?\" \u2013 us\u0142ysze\u0107 takie s\u0142owa od trzyletniej c\u00f3rki i zobaczy\u0107 jej strach w oczach oraz \u0142zy na policzkach, to dla rodzica jak ig\u0142a wbita w oko \u2013 opowiada czytelnik.\n\nKradzie\u017ce we W\u0142oszech \u2013 zuchwa\u0142o\u015b\u0107 z\u0142odziei i bezradno\u015b\u0107 policji\n\nJednak to nie kradzie\u017c najbardziej go zdumia\u0142a i zbulwersowa\u0142a. Prawdziwy szok prze\u017cy\u0142 dopiero wtedy, gdy postanowi\u0142 zg\u0142osi\u0107 j\u0105 na policj\u0119. Od m\u0142odej W\u0142oszki dowiedzia\u0142 si\u0119, \u017ce nie ma sensu wzywa\u0107 radiowozu, bo ten wysy\u0142any jest na miejsce zdarzenia tylko wtedy, gdy s\u0105 ofiary. Ka\u017cdy, kto chce zg\u0142osi\u0107 kradzie\u017c, musi sam pofatygowa\u0107 si\u0119 na posterunek.\n\nGdy polski turysta w ko\u0144cu na niego dotar\u0142, okaza\u0142o si\u0119, \u017ce \u017caden z jego pracownik\u00f3w nie m\u00f3wi po angielsku. Dlatego spisywanie protoko\u0142u trwa\u0142o trzy godziny i \u2013 jak twierdzi nasz czytelnik \u2013 by\u0142o najbardziej kuriozaln\u0105 cz\u0119\u015bci\u0105 tej nieweso\u0142ej przygody. Dokument powsta\u0142 dzi\u0119ki wsparciu internetowego t\u0142umacza, by\u0142 \"d\u0142ugim opisem samochodu i w dw\u00f3ch zdaniach zawiera\u0142 informacje o tym, \u017ce wybito w nim szyb\u0119 i skradziono baga\u017ce\".\n\nGdy okradziony turysta zapyta\u0142, czy jest szansa na odnalezienie jego rzeczy, policjant pozbawi\u0142 go z\u0142udze\u0144 \"W Katanii jest teraz bardzo du\u017co kradzie\u017cy. Nic z tym nie zrobimy\" \u2013 powiedzia\u0142 bez ogr\u00f3dek. Okaza\u0142o si\u0119, \u017ce z takim wysi\u0142kiem spisywany protok\u00f3\u0142 jest potrzebny jedynie do uzyskania ewentualnego odszkodowania od towarzystwa ubezpieczeniowego. Kiedy po czterech godzinach wype\u0142niania protoko\u0142u poszkodowany opu\u015bci\u0142 kwestur\u0119 policji, zosta\u0142 telefonicznie poinformowany, \u017ce... musi wr\u00f3ci\u0107. Tylko po to, by policjant m\u00f3g\u0142 przybi\u0107 na dokumencie piecz\u0105tk\u0119.\n\nPodobnie z\u0142e do\u015bwiadczenia z W\u0142och wywi\u00f3z\u0142 inny czytelnik \"Faktu\", kt\u00f3rego r\u00f3wnie\u017c okradziono w Katanii. I w tym przypadku policja nic nie zrobi\u0142a, nawet nie pofatygowa\u0142a si\u0119 na miejsce zdarzenia, co mocno rozgoryczy\u0142o turyst\u0119. \"W\u0142ochy podcinaj\u0105 ga\u0142\u0105\u017a, na kt\u00f3rej siedz\u0105. Ja ju\u017c wi\u0119cej tam nie pojad\u0119\" \u2013 podsumowa\u0142 dosadnie.\n\nJe\u017celi podr\u00f3\u017cuj\u0105c po W\u0142oszech, padniecie ofiar\u0105 kradzie\u017cy, od razu poszukajcie posterunku karabinier\u00f3w lub policji \u2013 tylko tam mo\u017cna spisa\u0107 protok\u00f3\u0142 upowa\u017cniaj\u0105cy do uzyskania odszkodowania. Jak najszybciej zastrze\u017ccie te\u017c zgubione lub skradzione karty p\u0142atnicze i kredytowe. Je\u017celi natomiast stracili\u015bcie dokumenty podr\u00f3\u017cy, skontaktujcie si\u0119 z Wydzia\u0142em Konsularnym i Polonii Ambasady RP w Rzymie, a w przypadku p\u00f3\u0142nocnych region\u00f3w W\u0142och \u2013 z Konsulatem Generalnym w Mediolanie.\n\n- / 123RF We W\u0142oszech lepiej nie zostawia\u0107 baga\u017cy w zaparkowanym samochodzie.\n\n- / 123RF W\u0142och zmagaj\u0105 si\u0119 z plag\u0105 kradzie\u017cy. Czytelnicy \"Faktu\" zostali okradzeni na Sycylii.\n\nPolacy ograbieni w turystycznym raju. \"Czu\u0142am si\u0119 obdarta ze wszystkiego\"\n\nPerfidny spos\u00f3b kieszonkowc\u00f3w w Rzymie. W takich przebraniach rabuj\u0105 senior\u00f3w"
        }
    },
    {
        "method": "POST",
        "headers": {
            "Content-Type": "application/json"
        },
        "body": {
            "title": "Polskie miasto p\u00f3jdzie drog\u0105 Wenecji? Jest apel o ograniczenie ha\u0142asu",
            "link": "https://www.msn.com/pl-pl/styl-zycia/moda-i-uroda/polskie-miasto-p%C3%B3jdzie-drog%C4%85-wenecji-jest-apel-o-ograniczenie-ha%C5%82asu/ar-AA1Dw9hY?ocid=BingNewsVerp",
            "description": "Krak\u00f3w na brak turyst\u00f3w nie narzeka. Ci cz\u0119sto spaceruj\u0105 po mie\u015bcie z walizkami, a to coraz mniej podoba si\u0119 mieszka\u0144com.",
            "image_url": "https://www.bing.pl/th?id=OVFT.GGBkX6Hp0hdmVNH8ZO1p9C&pid=News&w=234&h=132&c=14&rs=2&qlt=30",
            "category": "zabytkowe+przedmioty",
            "date": "Podr\u00f3\u017ce Wprost on MSN17 godz.",
            "source": "Podr\u00f3\u017ce Wprost on MSN",
            "article_content": ""
        }
    },
    {
        "method": "POST",
        "headers": {
            "Content-Type": "application/json"
        },
        "body": {
            "title": "Ten banknot 50 z\u0142otych jest wart fortun\u0119! A to nie jedyny okaz, kt\u00f3rego szukaj\u0105 kolekcjonerzy [25.04.2025 r.]",
            "link": "https://www.msn.com/pl-pl/wiadomosci/other/ten-banknot-50-z%C5%82otych-jest-wart-fortun%C4%99-a-to-nie-jedyny-okaz-kt%C3%B3rego-szukaj%C4%85-kolekcjonerzy-23042025/ar-AA1Dttas?ocid=BingNewsVerp",
            "description": "Banknot 50 z\u0142 z 1994 roku, oznaczony seri\u0105 zast\u0119pcz\u0105 YA to najrzadszy banknot III Rzeczypospolitej. Jak informuje portal W\u00f3jcicki - Polski Dom Aukcyjny - prawdopodobnie jest to tzw. rozbieg\u00f3wka.",
            "image_url": "https://www.bing.pl/th?id=ODF.qEcc-ZyVkvSOSXNTGhpADA&pid=news&w=16&h=16&c=14&rs=2&qlt=90",
            "category": "stare+numizmatyka",
            "date": "Gazeta Pomorska on MSN8 godz.",
            "source": "Gazeta Pomorska on MSN",
            "article_content": ""
        }
    },
    {
        "method": "POST",
        "headers": {
            "Content-Type": "application/json"
        },
        "body": {
            "title": "Plan B",
            "link": "https://warszawa.naszemiasto.pl/tag/plan-b",
            "description": "Na film czy do kina? W przypadku walentynkowej randki pewnie p\u00f3\u0142 na p\u00f3\u0142, bo raczej ju\u017c troch\u0119 si\u0119 znacie, skoro zapraszasz j\u0105 akurat 14 lutego do kina. Na co... \"Plan B\" to walentynkowa komedia, kt\u00f3ra ...",
            "image_url": "https://www.bing.pl/th?id=ODF.RiSZ6cVK2kGKUBp4PkSDCg&pid=news&w=16&h=16&c=14&rs=2&qlt=90",
            "category": "wykopano+zabytkowe",
            "date": "Warszawa Nasze Miasto7 godz.",
            "source": "Warszawa Nasze Miasto",
            "article_content": "Content not available"
        }
    }
]